<?xml version="1.0" encoding="ISO-8859-1"?>
<!DOCTYPE metadata SYSTEM "http://www.fgdc.gov/metadata/fgdc-std-001-1998.dtd">
<metadata>
	<idinfo>
		<citation>
			<citeinfo>
				<origin>U.S. Geological Survey</origin>
				<pubdate>200506</pubdate>
				<title>CONMAPSG: Continental Margin Mapping (CONMAP) sediments grainsize distribution for the United States East Coast Continental Margin</title>
				<edition>1.1</edition>
				<geoform>vector digital data</geoform>
				<serinfo>
					<sername>Open-File Report</sername>
					<issue>2005-1001</issue>
				</serinfo>
				<pubinfo>
					<pubplace>Woods Hole Science Center, Woods Hole, MA</pubplace>
					<publish>U.S. Geological Survey, Coastal and Marine Geology Program</publish>
				</pubinfo>
				<onlink>http://pubs.usgs.gov/of/2005/1001/data/conmapsg/conmapsg.zip</onlink>
				<onlink>http://pubs.usgs.gov/of/2005/1001/htmldocs/datacatalog.htm</onlink>
				<lworkcit>
					<citeinfo>
						<origin>L.J. Poppe</origin>
						<origin>S.J. Williams</origin>
						<origin>V.F. Paskevich</origin>
						<pubdate>2005</pubdate>
						<title>U.S. Geological Survey East-Coast Sediment Analysis: Procedures, Database, and GIS Data</title>
						<serinfo>
							<sername>Open-File Report</sername>
							<issue>2005-1001</issue>
						</serinfo>
						<pubinfo>
							<pubplace>Woods Hole Science Center, Woods Hole, MA</pubplace>
							<publish>U.S. Geological Survey, Coastal and Marine Geology Program</publish>
						</pubinfo>
						<othercit>Publication and data are released via digital media (either CD-ROM or DVD).  This digital publication may also be available via the web at pubs.usgs.gov</othercit>
						<onlink>http://pubs.usgs.gov/of/2005/1001/</onlink>
						<edition>1.0</edition></citeinfo>
				</lworkcit>
				<ftname Sync="TRUE">conmapsg</ftname></citeinfo>
		</citation>
		<descript>
			<abstract>Sediments off the eastern United States vary markedly in texture - the size, shape, and arrangement of their grains.  However, for descriptive purposes, it is typically most useful to classify these sediments according to their grain-size distributions. Starting in 1962, the U.S. Geological Survey (USGS) and the Woods Hole Oceanographic Institution (WHOI) began a joint program to study the marine geology of the continental margin off the Atlantic coast of the United States. As part of this program and numerous subsequent projects, thousands of sediment samples were collected and analyzed for particle size.

The sediment map of the Continental Margin Mapping Program (CONMAP) series is a compilation of grain-size data produced in the sedimentation laboratory of the Woods Hole Science Center (WHSC) of the Coastal and Marine Geology Program (CMGP) of the U.S. Geological Survey (USGS) and from both published and unpublished studies.  Sediment was classified using the Wentworth (1929) grain-size scale and the Shepard (1954) scheme of sediment classification. Certain grain-size categories are combined because of the paucity of some sediment textures; blank parts of the maps indicate areas where data are insufficient to infer sediment type. Bathymetry is used as a guide in placing some of the contacts between different sediment types.  However, because the true boundaries between sediment types are probably highly irregular or gradational, because the extreme textural variability that characterizes some areas does not appear at this scale, and because the accuracy of the navigational systems used during the earlier studies is limited, all contacts should be considered to be inferred.

The sediment classification for any given polygon (i.e. area) reflects the dominant surficial sediment type for that polygon.  It does not mean that other sediment types are not present within the polygon, only that the dominant sediment type is the one that is most common.</abstract>
			<purpose>The purpose of the CONMAPSG sediment layer is to show the sediment grain size distributions.  The maps depicted in this series are old and do not accurately depict small-scale sediment distributions or sea-floor variability.  This data layer is supplied primarily as a gross overview and to show general textural trends.</purpose>
			<langdata Sync="TRUE">en</langdata></descript>
		<timeperd>
			<timeinfo>
				<rngdates>
					<begdate>1982</begdate>
					<enddate>1999</enddate>
				</rngdates>
			</timeinfo>
			<current>ground condition</current>
		</timeperd>
		<status>
			<progress>Complete</progress>
			<update>Continually</update>
		</status>
		<spdom>
			<bounding>
				<westbc>
          -82.042793
        </westbc>
				<eastbc>
          -63.999992
        </eastbc>
				<northbc>
          45.216763
        </northbc>
				<southbc>
          24.011797
        </southbc>
			</bounding>
			<lboundng><leftbc Sync="TRUE">-82.042793</leftbc><rightbc Sync="TRUE">-63.999992</rightbc><bottombc Sync="TRUE">24.011797</bottombc><topbc Sync="TRUE">45.216763</topbc></lboundng></spdom>
		<keywords>
			<theme>
				<themekt>General</themekt>
				<themekey>U.S. Geological Survey</themekey>
				<themekey>USGS</themekey>
				<themekey>Coastal and Marine Geology Program</themekey>
				<themekey>CMGP</themekey>
				<themekey>Woods Hole Science Center</themekey>
				<themekey>WHSC</themekey>
				<themekey>ArcView shapefile</themekey>
				<themekey>surficial sediment</themekey>
				<themekey>polygons</themekey>
				<themekey>sediment type</themekey>
				<themekey>grain size</themekey>
				<themekey>sediment textural trends</themekey>
				<themekey>sediment distribution</themekey>
			</theme>
			<theme>
				<themekt>ISO 19115 Topic Category</themekt>
				<themekey>oceans and estuaries</themekey>
				<themekey>boundaries</themekey>
				<themekey>geoscientificInformation</themekey>
			</theme>
			<place>
				<placekt>General</placekt>
				<placekey>Eastern U.S.</placekey>
				<placekey>Exclusive Economic Zone</placekey>
				<placekey>coastal ocean</placekey>
				<placekey>Atlantic East Coast</placekey>
				<placekey>east coast</placekey>
				<placekey>Georges Bank</placekey>
				<placekey>Gulf of Maine</placekey>
				<placekey>Baltimore Canyon Trough</placekey>
				<placekey>Carolina Trough</placekey>
				<placekey>Blake Plateau</placekey>
			</place>
		</keywords>
		<accconst>None</accconst>
		<useconst>Public domain data from the U.S. Government are freely redistributable with proper metadata and source attribution.  Please recognize the U.S. Geological Survey (USGS) as the source of this information.</useconst>
		<ptcontac>
			<cntinfo>
				<cntperp>
					<cntper>Larry Poppe</cntper>
					<cntorg>U.S. Geological Survey</cntorg>
				</cntperp>
				<cntpos>Geologist</cntpos>
				<cntaddr>
					<addrtype>mailing and physical address</addrtype>
					<address>384 Woods Hole Road</address>
					<city>Woods Hole</city>
					<state>MA</state>
					<postal>02543-1598</postal>
					<country>USA</country>
				</cntaddr>
				<cntvoice>(508) 548-8700 x2314</cntvoice>
				<cntfax>(508-) 457-2310</cntfax>
				<cntemail>lpoppe@usgs.gov</cntemail>
				<hours>Monday-Friday, 8am-5pm, Eastern Standard Time</hours>
			</cntinfo>
		</ptcontac>
		<browse>
			<browsen>http://pubs.usgs.gov/of/2005/1001/data/conmapsg/conmapsg-thumb.gif</browsen>
			<browsed>Thumbnail image showing distribution and extent of data layer along the U.S. East Coast</browsed>
			<browset>GIF</browset>
		</browse>
		<browse>
			<browsen>http://pubs.usgs.gov/of/2005/1001/data/conmapsg/conmapsg.gif</browsen>
			<browsed>Thumbnail image showing distribution and extent of data layer along the U.S. East Coast</browsed>
			<browset>GIF</browset>
		</browse>
		<native>Microsoft Windows XP Version 5.1 (Build 2600) Service Pack 2; ESRI ArcCatalog 9.0.0.535</native>
		<crossref>
			<citeinfo>
				<origin>Lawrence J. Poppe (ed.)</origin>
				<origin>Chris Polloni(ed.)</origin>
				<pubdate>20000501</pubdate>
				<title>USGS East-Coast Sediment Analysis: Procedures, Database, and Georeferenced Displays</title>
				<serinfo>
					<sername>Open File Report</sername>
					<issue>00-358</issue>
				</serinfo>
				<pubinfo>
					<pubplace>Woods Hole Science Center, Woods Hole, MA</pubplace>
					<publish>U.S. Geological Survey, Coastal and Marine Geology Program</publish>
				</pubinfo>
				<othercit>Data are released via CD-ROM media.  The publication may also be available online at pubs.usgs.gov</othercit>
				<onlink>http://pubs.usgs.gov/of/of00-358/</onlink>
			</citeinfo>
		</crossref>
		<crossref>
			<citeinfo>
				<origin>Poppe, L.J.</origin>
				<origin>Schlee, J.S.</origin>
				<origin>Butman, B.</origin>
				<origin>Lane, C.M.</origin>
				<pubdate>1989</pubdate>
				<title>Map showing distribution of surficial sediment, Gulf of Maine and Georges Banks</title>
				<serinfo>
					<sername>IMAP</sername>
					<issue>1986-A</issue>
				</serinfo>
				<pubinfo>
					<pubplace>Woods Hole Science Center, Woods Hole, MA</pubplace>
					<publish>U.S. Geological Survey, Coastal and Marine Geology Program</publish>
				</pubinfo>
				<othercit></othercit>
				<onlink></onlink>
			</citeinfo>
		</crossref>
		<crossref>
			<citeinfo>
				<origin>Poppe, L.J.</origin>
				<origin>Schlee, J.S.</origin>
				<origin>Knebel, H.J.</origin>
				<pubdate>1994</pubdate>
				<title>Map showing distribution of surficial sediment on the mid-Atlantic continental margin, Cape Cod to Albemarle Sound</title>
				<serinfo>
					<sername>IMAP</sername>
					<issue>1987-D</issue>
				</serinfo>
				<pubinfo>
					<pubplace>Woods Hole Science Center, Woods Hole, MA</pubplace>
					<publish>U.S. Geological Survey, Coastal and Marine Geology Program</publish>
				</pubinfo>
				<othercit></othercit>
				<onlink></onlink>
			</citeinfo>
		</crossref>
		<natvform Sync="TRUE">Shapefile</natvform></idinfo>
	<dataqual>
		<attracc>
			<attraccr>The assigned sediment attributes in this data set are believed to be accurate.  The sediment classification for any given polygon (i.e. area) reflects the dominant surficial sediment type for that polygon.  It does not mean that other sediment types are not present within the polygon, only that the dominant sediment type is the one that is most common.</attraccr>
		</attracc>
		<logic>These data are believed to be logically consistent, although not tested. Geometry appears to be topologically clean.</logic>
		<complete>This dataset covers the GLORIA project area for the United States East Coast Atlantic Ocean Exclusive Economic Zone (EEZ) area.</complete>
		<posacc>
			<horizpa>
				<horizpar>The accuracy of this dataset is based on source data that is assumed to have met National Map Accuracy Standards</horizpar>
			</horizpa>
			<vertacc>
			</vertacc>
		</posacc>
		<lineage>
			<srcinfo>
				<srccite>
					<citeinfo>
						<origin>Poppe, L.J.</origin>
						<origin>Schlee, J.S.</origin>
						<origin>Butman, B.</origin>
						<origin>Lane, C.M.</origin>
						<pubdate>1989</pubdate>
						<title>Map Showing the distribution of surficial sediment, Gulf of Maine and Georges Bank</title>
						<edition>1.0</edition>
						<geoform>map</geoform>
						<serinfo>
							<sername>IMAP</sername>
							<issue>1986-A</issue>
						</serinfo>
						<pubinfo>
							<pubplace>Reston, VA</pubplace>
							<publish>U.S. Geological Survey, Coastal and Marine Geology Program</publish>
						</pubinfo>
						<lworkcit>
							<citeinfo>
								<pubinfo>
								</pubinfo>
							</citeinfo>
						</lworkcit>
					</citeinfo>
				</srccite>
				<srcscale>1000000</srcscale>
				<typesrc>paper</typesrc>
				<srctime>
					<timeinfo>
						<sngdate>
							<caldate>1989</caldate>
						</sngdate>
					</timeinfo>
					<srccurr>publication date</srccurr>
				</srctime>
				<srccitea>IMAP 1987-D</srccitea>
				<srccontr>Map was used as source during process of digitizing sediment polygons.</srccontr>
			</srcinfo>
			<srcinfo>
				<srccite>
					<citeinfo>
						<origin>Poppe, L.J.</origin>
						<origin>Schlee, J.S.</origin>
						<origin>Knebel, H.J</origin>
						<pubdate>1994</pubdate>
						<title>Map showing distribution of surficial sediment on the mid-Atlantic continental margin, Cape Cod to Albemarle Sound</title>
						<edition>1.0</edition>
						<geoform>map</geoform>
						<serinfo>
							<sername>IMAP</sername>
							<issue>1987-D</issue>
						</serinfo>
						<pubinfo>
							<pubplace>Reston, VA</pubplace>
							<publish>U.S. Geological Survey, Coastal and Marine Geology Program</publish>
						</pubinfo>
					</citeinfo>
				</srccite>
				<srcscale>1000000</srcscale>
				<typesrc>paper</typesrc>
				<srctime>
					<timeinfo>
						<sngdate>
							<caldate>1994</caldate>
						</sngdate>
					</timeinfo>
					<srccurr>publication date</srccurr>
				</srctime>
				<srccitea>IMAP 1987-D</srccitea>
				<srccontr>Map was used as source during process of digitizing sediment polygons.</srccontr>
			</srcinfo>
			<srcinfo>
				<srccite>
					<citeinfo>
						<origin>Poppe, L.J.</origin>
						<origin>Lane, C.M.</origin>
						<pubdate>Unpublished Material</pubdate>
						<title>showing distribution of surficial sediment on the mid-Atlantic continental margin and Carolina Trough, Albemarle Sound to Charleston</title>
						<edition>1.0</edition>
						<geoform>map</geoform>
					</citeinfo>
				</srccite>
				<srcscale>1000000</srcscale>
				<typesrc>paper</typesrc>
				<srctime>
					<timeinfo>
						<sngdate>
							<caldate>1989</caldate>
						</sngdate>
					</timeinfo>
				</srctime>
				<srccitea>unpublished Mid-Atlantic continental margin map</srccitea>
				<srccontr>was used as source during process of digitizing sediment polygons.</srccontr>
			</srcinfo>
			<srcinfo>
				<srccite>
					<citeinfo>
						<origin>Poppe, L.J.</origin>
						<origin>Lane, C.M.</origin>
						<pubdate>Unpublished Material</pubdate>
						<title>Map showing distribution of surficial sediment on the south-Atlantic continental margin and Blake Plateau</title>
						<edition>1.0</edition>
						<geoform>map</geoform>
					</citeinfo>
				</srccite>
				<srcscale>1000000</srcscale>
				<typesrc>paper</typesrc>
				<srctime>
					<timeinfo>
						<sngdate>
							<caldate>1989</caldate>
						</sngdate>
					</timeinfo>
				</srctime>
				<srccitea>unpublished map of the south-Atlantic continental margin and Blake Plateau</srccitea>
				<srccontr>Map was used as source during process of digitizing sediment polygons.</srccontr>
			</srcinfo>
			<procstep>
				<procdesc>Source maps from the Gulf of Maine and Georges Bank and the mid-Atlantic, Cape Cod to Albemarle Sound were digitized in PC Arc Info to create a vector line data set of sediment polygon boundaries, registered to the NOAA medium-resolution shoreline, and processed to create a polygon dataset.</procdesc>
				<srcused>IMAP 1986-A</srcused>
				<srcused>IMAP 1987-D</srcused>
				<procdate>1995</procdate>
				<srcprod>vector line data</srcprod>
				<srcprod>nat_sed.e00</srcprod>
				<proccont>
					<cntinfo>
						<cntperp>
							<cntper>Kevin Joy</cntper>
							<cntorg>National Underwater Research Center</cntorg>
						</cntperp>
						<cntpos>GIS Specialist</cntpos>
						<cntaddr>
							<addrtype>mailing and physical address</addrtype>
							<address>1084 Shennecossett Road</address>
							<city>Groton</city>
							<state>CT</state>
							<postal>06340</postal>
							<country>USA</country>
						</cntaddr>
						<cntvoice>(860) 405-9112</cntvoice>
						<cntfax></cntfax>
						<cntemail>kevin.joy@uconn.edu</cntemail>
					</cntinfo>
				</proccont>
			</procstep>
			<procstep>
				<procdesc>Source maps from the remaining two areas (Carolina Trough, Albemarle Sound to Charleston and South Atlantic and Blake Plateau) were digitized to create a vector line data set of sediment polygon boundaries.</procdesc>
				<srcused>unpublished Mid-Atlantic continental margin map</srcused>
				<srcused>unpublished map of the south-Atlantic continental margin and Blake Plateau</srcused>
				<procdate>2000</procdate>
				<srcprod>vector line data</srcprod>
				<proccont>
					<cntinfo>
						<cntperp>
							<cntper>Larry Poppe</cntper>
							<cntorg>U.S. Geological Survey</cntorg>
						</cntperp>
						<cntpos>Geologist</cntpos>
						<cntaddr>
							<addrtype>mailing and physical address</addrtype>
							<address>384 Woods Hole Road</address>
							<city>Woods Hole</city>
							<state>MA</state>
							<postal>02543-1598</postal>
							<country>USA</country>
						</cntaddr>
						<cntvoice>(508) 548-8700 x2314</cntvoice>
						<cntfax>(508) 457-2310</cntfax>
						<cntemail>lpoppe@usgs.gov</cntemail>
					</cntinfo>
				</proccont>
			</procstep>
			<procstep>
				<procdesc>The "line" data generated from digitizing the sediment boundaries of the Carolina Trough, Albemarle Sound to Charleston and the South Atlantic and Blake Plateau areas were registered to the NOAA medium-resolution shoreline, combined with the data from the Gulf of Maine and Georges Bank and the mid-Atlantic, Cape Cod to Albemarle Sound, and processed in ArcInfo to create the a polygon dataset of the entire U.S. east coast.</procdesc>
				<procdate>20000718</procdate>
				<srcprod>conmapsg.dbf</srcprod>
				<srcprod>conmapsg.shp</srcprod>
				<srcprod>conmapsg.shx</srcprod>
				<proccont>
					<cntinfo>
						<cntperp>
							<cntper>Dan Martin</cntper>
							<cntorg>TPMC</cntorg>
						</cntperp>
						<cntpos>Senior GIS Analyst</cntpos>
						<cntaddr>
							<addrtype>mailing and physical address</addrtype>
							<address>Mill Wharf Plaza, suite 208</address>
							<city>Scituate</city>
							<state>MA</state>
							<postal>02066</postal>
							<country>USA</country>
						</cntaddr>
						<cntvoice>(781) 544-0026</cntvoice>
						<cntfax>(781) 544-3086</cntfax>
						<cntemail>dmartin@tpmc.com</cntemail>
						<hours>Monday-Friday, 8am-5pm, EST</hours>
					</cntinfo>
				</proccont>
				<srcused>vector line data</srcused></procstep>
			<procstep>
				<procdesc>Removed the "land" and "no data" polygons and the ArcInfo fields from the shapefile.</procdesc>
				<srcused>conmapsg.dbf</srcused>
				<srcused>conmapsg.shp</srcused>
				<srcused>conmapsg.shx</srcused>
				<procdate>20041219</procdate>
				<srcprod>conmapsg.dbf</srcprod>
				<srcprod>conmapsg.shp</srcprod>
				<srcprod>conmapsg.shx</srcprod>
				<proccont>
					<cntinfo>
						<cntperp>
							<cntper>Valerie Paskevich</cntper>
							<cntorg>U.S. Geological Survey</cntorg>
						</cntperp>
						<cntpos>Information Technology Specialist, GIS Coordinator</cntpos>
						<cntaddr>
							<addrtype>mailing and physical address</addrtype>
							<address>384 Woods Hole Road</address>
							<city>Woods Hole</city>
							<state>MA</state>
							<postal>02543-1598</postal>
							<country>USA</country>
						</cntaddr>
						<cntvoice>(508) 548-8700 x2281</cntvoice>
						<cntfax>(508) 457-2310</cntfax>
						<cntemail>vpaskevich@usgs.gov</cntemail>
					</cntinfo>
				</proccont>
			</procstep>
			<procstep><srcused>conmapsg.dbf</srcused><srcprod>conmapsg.dbf</srcprod><proccont><cntinfo><cntperp><cntper>Valerie Paskevich</cntper><cntorg>U.S. Geological Survey</cntorg></cntperp><cntpos>Information Specialist, GIS Coordinator</cntpos><cntaddr><addrtype>mailing and physical address</addrtype><address>384 Woods Hole Road</address><city>Woods Hole</city><state>MA</state><postal>02543-1598</postal><country>USA</country></cntaddr><cntvoice>(508) 548-8700 x2281</cntvoice><cntfax>(508) 457-2310</cntfax><cntemail>vpaskevich@usgs.gov</cntemail></cntinfo></proccont><procdesc>Merged some polygons that had previously been divided by old Continental Margin Mapping Program boundaries.  The split polygons showed unnecessary boundaries.  Combining the polygons provides a better representation of the East Coast dataset.</procdesc><procsv>ArcView 3.3 and XTOOLS</procsv><srcused>conmapsg.shp</srcused><procdate>20041220</procdate><srcprod>conmapsg.shp</srcprod></procstep></lineage>
	</dataqual>
	<spdoinfo>
		<direct>Vector</direct>
		<ptvctinf>
			<sdtsterm Name="conmapsg">
				<sdtstype>G-polygon</sdtstype>
				<ptvctcnt>19662</ptvctcnt>
			</sdtsterm>
			<esriterm Name="conmapsg"><efeatyp Sync="TRUE">Simple</efeatyp><efeageom Sync="TRUE">Polygon</efeageom><esritopo Sync="TRUE">FALSE</esritopo><efeacnt Sync="TRUE">376</efeacnt><spindex Sync="TRUE">FALSE</spindex><linrefer Sync="TRUE">FALSE</linrefer></esriterm></ptvctinf>
	</spdoinfo>
	<spref>
		<horizsys>
			<geograph>
				<latres>0.00001</latres>
				<longres>0.00001</longres>
				<geogunit>Decimal degrees</geogunit>
			</geograph>
			<geodetic>
				<horizdn>North American Datum of 1983</horizdn>
				<ellips>Geodetic Reference System 80</ellips>
				<semiaxis>6,378,137</semiaxis>
				<denflat>298.257</denflat>
			</geodetic>
			<cordsysn><geogcsn Sync="TRUE">GCS_North_American_1983</geogcsn></cordsysn></horizsys>
	</spref>
	<eainfo>
		<detailed Name="conmapsg">
			<enttyp>
				<enttypl>
          conmapsg
        </enttypl>
				<enttypd>Shapefile Attribute Table</enttypd>
				<enttypds>ESRI</enttypds>
				<enttypt Sync="TRUE">Feature Class</enttypt><enttypc Sync="TRUE">376</enttypc></enttyp>
			<attr>
				<attrlabl>FID</attrlabl>
				<attrdef>Internal feature number.</attrdef>
				<attrdefs>ESRI</attrdefs>
				<attrdomv>
					<udom>Sequential unique whole numbers that are automatically generated.</udom>
				</attrdomv>
			</attr>
			<attr>
				<attrlabl>Shape</attrlabl>
				<attrdef>Feature geometry.</attrdef>
				<attrdefs>ESRI</attrdefs>
				<attrdomv>
					<udom>Coordinates defining the features.</udom>
				</attrdomv>
			</attr>
			<attr>
				<attrlabl>AREA</attrlabl>
				<attrdef>Area of polygon in native units</attrdef>
				<attrdefs>Software Computed</attrdefs>
				<attrtype Sync="TRUE">Number</attrtype><attwidth Sync="TRUE">12</attwidth><atnumdec Sync="TRUE">3</atnumdec></attr>
			<attr>
				<attrlabl>PERIMETER</attrlabl>
				<attrdef>Length of polygon perimeter in native units</attrdef>
				<attrdefs>Software Computed</attrdefs>
				<attrtype Sync="TRUE">Number</attrtype><attwidth Sync="TRUE">12</attwidth><atnumdec Sync="TRUE">3</atnumdec></attr>
			<attr>
				<attrlabl>SEDIMENT</attrlabl>
				<attrdef>Assigned code describing sediment.</attrdef>
				<attrdefs>U.S. Geological Survey</attrdefs>
				<attrdomv>
					<udom>Character String</udom>
				</attrdomv>
				<attrdomv>
					<edom>
						<edomv>br</edomv>
						<edomvd>bedrock</edomvd>
						<edomvds>U.S. Geological Survey</edomvds>
					</edom>
					<edom>
						<edomv>gr</edomv>
						<edomvd>gravel</edomvd>
						<edomvds>U.S. Geological Survey</edomvds>
					</edom>
					<edom>
						<edomv>gr-sd</edomv>
						<edomvd>gravel-sand</edomvd>
						<edomvds>U.S. Geological Survey</edomvds>
					</edom>
					<edom>
						<edomv>sd</edomv>
						<edomvd>sand</edomvd>
						<edomvds>U.S. Geological Survey</edomvds>
					</edom>
					<edom>
						<edomv>cl-st/sd</edomv>
						<edomvd>clay-silt/sand</edomvd>
						<edomvds>U.S. Geological Survey</edomvds>
					</edom>
					<edom>
						<edomv>sd/st/cl</edomv>
						<edomvd>sand/silt/clay</edomvd>
						<edomvds>U.S. Geological Survey</edomvds>
					</edom>
					<edom>
						<edomv>sd-cl/st</edomv>
						<edomvd>sand-clay/silt</edomvd>
						<edomvds>U.S. Geological Survey</edomvds>
					</edom>
					<edom>
						<edomv>sd-st/cl</edomv>
						<edomvd>sand-silt/clay</edomvd>
						<edomvds>U.S. Geological Survey</edomvds>
					</edom>
					<edom>
						<edomv>cl</edomv>
						<edomvd>clay</edomvd>
						<edomvds>U.S. Geological Survey</edomvds>
					</edom>
				</attrdomv>
				<attrtype Sync="TRUE">String</attrtype><attwidth Sync="TRUE">12</attwidth></attr>
			<attr>
				<attrlabl>SEDNUM</attrlabl>
				<attrdef>Assigned code describing sediment</attrdef>
				<attrdefs>U.S. Geological Survey</attrdefs>
				<attrdomv>
					<rdom>
						<rdommin>1</rdommin>
						<rdommax>9</rdommax>
						<attrunit>1</attrunit>
						<attrmres>integer count</attrmres>
					</rdom>
				</attrdomv>
				<attrdomv>
					<edom>
						<edomv>1</edomv>
						<edomvd>bedrock</edomvd>
						<edomvds>USGS</edomvds>
					</edom>
					<edom>
						<edomv>2</edomv>
						<edomvd>gravel</edomvd>
						<edomvds>USGS</edomvds>
					</edom>
					<edom>
						<edomv>3</edomv>
						<edomvd>gravel-sand</edomvd>
						<edomvds>USGS</edomvds>
					</edom>
					<edom>
						<edomv>4</edomv>
						<edomvd>sand</edomvd>
						<edomvds>USGS</edomvds>
					</edom>
					<edom>
						<edomv>5</edomv>
						<edomvd>clay-silt/sand</edomvd>
						<edomvds>USGS</edomvds>
					</edom>
					<edom>
						<edomv>6</edomv>
						<edomvd>sand-clay/silt</edomvd>
						<edomvds>USGS</edomvds>
					</edom>
					<edom>
						<edomv>7</edomv>
						<edomvd>clay</edomvd>
						<edomvds>USGS</edomvds>
					</edom>
					<edom>
						<edomv>8</edomv>
						<edomvd>sand-silt/clay</edomvd>
						<edomvds>USGS</edomvds>
					</edom>
					<edom>
						<edomv>9</edomv>
						<edomvd>sand/silt/clay</edomvd>
						<edomvds>USGS</edomvds>
					</edom>
				</attrdomv>
				<attrtype Sync="TRUE">Number</attrtype><attwidth Sync="TRUE">11</attwidth></attr>
		</detailed>
		<overview>
			<dsoverv>The assigned sediment attributes in this data set are believed to be accurate.  The sediment classification for any given polygon (i.e. area) reflects the dominant surficial sediment type for that polygon.  It does not mean that other sediment types are not present within the polygon, only that the dominant sediment type is the one that is most common.</dsoverv></overview>
	</eainfo>
	<distinfo>
		<distrib>
			<cntinfo>
				<cntperp>
					<cntper>Larry Poppe</cntper>
					<cntorg>U.S. Geological Survey</cntorg>
				</cntperp>
				<cntpos>Geologist</cntpos>
				<cntaddr>
					<addrtype>mailing and physical address</addrtype>
					<address>384 Woods Hole Road</address>
					<city>Woods Hole</city>
					<state>MA</state>
					<postal>02543-1598</postal>
					<country>USA</country>
				</cntaddr>
				<cntvoice>(508) 548-8700 x2314</cntvoice>
				<cntfax>(508) 457-2310</cntfax>
				<cntemail>lpoppe@usgs.gov</cntemail>
			</cntinfo>
		</distrib>
		<resdesc>Downloadable Data</resdesc>
		<distliab>Although this derived data set and its lineage dataset have been used by the USGS, no warranty, expressed or implied, is made by the USGS as to the accuracy of the data and/or related materials.  The act of distribution shall not constitute any such warranty, and no responsibility is assumed by the USGS in the use of these data or related materials.

Trade, firm, or product names and other references to non-USGS products and services are provided for information only and do not constitute endorsement or warranty, express or implied, by the USGS, USDOI, or U.S. Government, as to their suitability, content, usefulness, functioning, completeness, or accuracy.</distliab>
		<stdorder>
			<digform>
				<digtinfo>
					<formname>Shapefile</formname>
					<formvern>ArcView 3.3</formvern>
					<formcont>The SHP file contains the geospatial data. The SHX file contains the index of the geospatial data. The DBF file contains the attribute data in dBASE format. The PRJ file contains the coordinate system information (optional). The AVL file contains the legend information (optional). The SBN and SBX files contain the spatial index of the geospatial data (optional). The XML file contains the metadata describing the data set &lt;data set name&gt;.shp.xml.  An ASCII version of the metadata file.  A browse graphic showing the data layer coverage and extent (optional).</formcont>
					<filedec>zip</filedec>
					<transize>11.982 Kbytes</transize>
					<dssize Sync="TRUE">14.007</dssize><formspec>ESRI Shapefile</formspec></digtinfo>
				<digtopt>
					<onlinopt>
						<computer>
							<networka>
								<networkr>http://pubs.usgs.gov/of/2005/1001/data/congmapsg/conmapsg.zip</networkr>
								<networkr>http://pubs.usgs.gov/of/2005/1001/data/congmapsg/</networkr></networka>
						</computer>
						<accinstr>Data are downloadable via the World Wide Web (WWW).</accinstr></onlinopt>
				</digtopt>
			</digform>
			<fees>None</fees>
		</stdorder>
		<techpreq>These data are available in Environmental Systems Research Institute (ESRI) shapefile format.  The user must have ArcGIS® or ArcView® 3.0 or greater software to read and process the data file.  In lieu of ArcView or ArcGIS, the user may utilize another GIS application package capable of importing data.  A free data viewer, arcexplorer, capable of displaying the data is available from ESRI at www.esri.com.</techpreq>
	</distinfo>
	<metainfo>
		<metd>20041220</metd>
		<metc>
			<cntinfo>
				<cntperp>
					<cntper>Valerie Paskevich</cntper>
					<cntorg>U.S. Geological Survey</cntorg>
				</cntperp>
				<cntpos>Information Technology Specialist, GIS Coordinator</cntpos>
				<cntaddr>
					<addrtype>mailing and physical address</addrtype>
					<address>384 Woods Hole Road</address>
					<city>Woods Hole</city>
					<state>MA</state>
					<postal>02543-1598</postal>
					<country>USA</country>
				</cntaddr>
				<cntvoice>(508) 548-8700 x2281</cntvoice>
				<cntfax>(508) 457-2310</cntfax>
				<cntemail>vpaskevich@usgs.gov</cntemail>
			</cntinfo>
		</metc>
		<metstdn>FGDC Content Standards for Digital Geospatial Metadata</metstdn>
		<metstdv>FGDC-STD-001-1998</metstdv>
		<mettc>local time</mettc>
		<metac>None</metac>
		<metuc>None</metuc>
		<langmeta Sync="TRUE">en</langmeta><metrd>20050513</metrd><metextns><onlink Sync="TRUE">http://www.esri.com/metadata/esriprof80.html</onlink><metprof Sync="TRUE">ESRI Metadata Profile</metprof></metextns></metainfo>
	<dataIdInfo><envirDesc Sync="TRUE">Microsoft Windows XP Version 5.1 (Build 2600) Service Pack 2; ESRI ArcCatalog 9.0.0.535</envirDesc><dataLang><languageCode Sync="TRUE" value="en"></languageCode></dataLang><idCitation><resTitle Sync="TRUE">conmapsg</resTitle><presForm><PresFormCd Sync="TRUE" value="005"></PresFormCd></presForm></idCitation><spatRpType><SpatRepTypCd Sync="TRUE" value="001"></SpatRepTypCd></spatRpType><dataExt><geoEle><GeoBndBox esriExtentType="native"><westBL Sync="TRUE">-82.042793</westBL><eastBL Sync="TRUE">-63.999992</eastBL><northBL Sync="TRUE">45.216763</northBL><southBL Sync="TRUE">24.011797</southBL><exTypeCode Sync="TRUE">1</exTypeCode></GeoBndBox></geoEle></dataExt><geoBox esriExtentType="decdegrees"><westBL Sync="TRUE">-82.042793</westBL><eastBL Sync="TRUE">-63.999992</eastBL><northBL Sync="TRUE">45.216763</northBL><southBL Sync="TRUE">24.011797</southBL><exTypeCode Sync="TRUE">1</exTypeCode></geoBox></dataIdInfo><mdLang><languageCode Sync="TRUE" value="en"></languageCode></mdLang><mdStanName Sync="TRUE">ISO 19115 Geographic Information - Metadata</mdStanName><mdStanVer Sync="TRUE">DIS_ESRI1.0</mdStanVer><mdChar><CharSetCd Sync="TRUE" value="004"></CharSetCd></mdChar><mdHrLv><ScopeCd Sync="TRUE" value="005"></ScopeCd></mdHrLv><mdHrLvName Sync="TRUE">dataset</mdHrLvName><distInfo><distributor><distorTran><onLineSrc><orDesc Sync="TRUE">002</orDesc><linkage Sync="TRUE">file://\\VALPASDTXP\D$\my webs\texture\data\conmapsg\conmapsg.shp</linkage><protocol Sync="TRUE">Local Area Network</protocol></onLineSrc><transSize Sync="TRUE">14.007</transSize></distorTran><distorFormat><formatName Sync="TRUE">Shapefile</formatName></distorFormat></distributor></distInfo><refSysInfo><RefSystem><refSysID><identCode Sync="TRUE">GCS_North_American_1983</identCode></refSysID></RefSystem></refSysInfo><spatRepInfo><VectSpatRep><topLvl><TopoLevCd Sync="TRUE" value="001"></TopoLevCd></topLvl><geometObjs Name="conmapsg"><geoObjTyp><GeoObjTypCd Sync="TRUE" value="001"></GeoObjTypCd></geoObjTyp><geoObjCnt Sync="TRUE">376</geoObjCnt></geometObjs></VectSpatRep></spatRepInfo><Esri><SyncDate>20050817</SyncDate><SyncTime>08571800</SyncTime><ModDate>20050817</ModDate><ModTime>09232400</ModTime></Esri><mdDateSt Sync="TRUE">20050817</mdDateSt></metadata>
