<metadata xml:lang="en"><dataIdInfo><envirDesc>Microsoft Windows XP Version 5.1 (Build 2600) Service Pack 3; ESRI ArcGIS 10.0.0.2414</envirDesc><dataLang><languageCode value="" country="US"/><countryCode value="USA" Sync="TRUE"/></dataLang><idCitation xmlns=""><resTitle>Sand_Gravel_05112012</resTitle><presForm xmlns=""><PresFormCd value="005"/></presForm><resAltTitle>BOEM Sand and Gravel Borrow Areas</resAltTitle><resEdDate>20120511</resEdDate><citId xmlns=""><identCode>BOEM Marine Minerals Program - Sand and Gravel Borrow Areas - combined</identCode></citId><citRespParty xmlns=""><rpIndName>Leasing Division Chief</rpIndName><rpOrgName>BOEM, Office of Strategic Resources</rpOrgName><rpPosName>Chief</rpPosName><role><RoleCd value="007"/></role><rpCntInfo><cntAddress><delPoint>381 Elden Street</delPoint><city>Herndon</city><adminArea>VA</adminArea><postCode>20170</postCode><eMailAdd>charlie.broadwater@boem.gov</eMailAdd><country>USA</country></cntAddress><cntPhone><voiceNum>703-787-1215</voiceNum></cntPhone><cntHours>8AM - 5PM EST</cntHours><cntInstr>Call</cntInstr></rpCntInfo></citRespParty></idCitation><descKeys><thesaName uuidref="723f6998-058e-11dc-8314-0800200c9a66"/><keyword>002</keyword></descKeys><spatRpType><SpatRepTypCd value="001"/></spatRpType><searchKeys><keyword>Sand</keyword><keyword>Gravel</keyword><keyword>Minerals</keyword><keyword>Marine Minerals Program</keyword><keyword>Beach Renourishment</keyword><keyword>Dredge</keyword><keyword>MidAtlantic</keyword><keyword>South Atlantic</keyword><keyword>Gulf of Mexico</keyword></searchKeys><dataExt xmlns=""><geoEle><GeoBndBox esriExtentType="search"><westBL>-93.762650</westBL><eastBL>-75.029863</eastBL><northBL>38.260833</northBL><southBL>26.389950</southBL><exTypeCode>1</exTypeCode></GeoBndBox><GeoBndBox esriExtentType="native"><westBL Sync="TRUE">-93.76265</westBL><eastBL Sync="TRUE">-75.029863</eastBL><northBL Sync="TRUE">38.260833</northBL><southBL Sync="TRUE">26.38995</southBL><exTypeCode Sync="TRUE">1</exTypeCode></GeoBndBox></geoEle></dataExt><idPurp>These areas will provide users a more accurate delineation of sand that has a high potential for use in shore protection, beach nourishment and/or wetlands restoration projects.
</idPurp><idAbs>&lt;DIV STYLE="text-align:Left;"&gt;&lt;DIV&gt;&lt;DIV&gt;&lt;P&gt;&lt;SPAN&gt;This data set contains both Authorized Borrow Areas (ABAs) and Potential Borrow Areas (PBAs), in ESRI shape file format, for the Atlantic and Gulf of Mexico Regions. These areas are not precise coordinates and may be off from the actual defined areas. &lt;/SPAN&gt;&lt;/P&gt;&lt;P&gt;&lt;SPAN&gt;There are two terms used Authorized Borrow Areas and Potential Borrow Areas. An Authorized Borrow Area can be defined as a specific area identified for use in a specific project (or that has been used previously in a nourishment project). A Potential Borrow Area can be defined as an area where work is being done to identify a specific borrow area (studies, recon, etc.).&lt;/SPAN&gt;&lt;/P&gt;&lt;P&gt;&lt;SPAN /&gt;&lt;SPAN /&gt;&lt;/P&gt;&lt;P&gt;&lt;SPAN /&gt;&lt;/P&gt;&lt;/DIV&gt;&lt;/DIV&gt;&lt;/DIV&gt;</idAbs><idCredit>Christine Taylor and Charlie Broadwater.  Leasing Division, Office of Strategic Resources, Bureau of Ocean Energy Management, Dept. of Interior</idCredit><resConst><Consts xmlns=""><useLimit>&lt;DIV STYLE="text-align:Left;"&gt;&lt;DIV&gt;&lt;DIV&gt;&lt;P&gt;&lt;SPAN&gt;For general planning purposes only. Contact the Marine Minerals program within the Leasing Division for specific information.&lt;/SPAN&gt;&lt;/P&gt;&lt;/DIV&gt;&lt;/DIV&gt;&lt;/DIV&gt;</useLimit></Consts></resConst><dataChar><CharSetCd value="004"></CharSetCd></dataChar><idPoC xmlns=""><rpIndName>Charles Broadwater</rpIndName><rpOrgName>BOEM - Leasing Division - Marine Minerals</rpOrgName><rpPosName>Program Analyst</rpPosName><role><RoleCd value="005"></RoleCd></role></idPoC><resMaint xmlns=""><maintFreq><MaintFreqCd value="009"></MaintFreqCd></maintFreq></resMaint><tpCat><TopicCatCd value="007"/></tpCat><tpCat><TopicCatCd value="008"/></tpCat><tpCat><TopicCatCd value="014"/></tpCat><geoBox esriExtentType="decdegrees"><westBL Sync="TRUE">-93.76265</westBL><eastBL Sync="TRUE">-75.029863</eastBL><northBL Sync="TRUE">38.260833</northBL><southBL Sync="TRUE">26.38995</southBL><exTypeCode Sync="TRUE">1</exTypeCode></geoBox><idPoC Sync="TRUE"><rpIndName Sync="TRUE">Leasing Division Chief</rpIndName><rpOrgName Sync="TRUE">BOEM, Office of Strategic Resources</rpOrgName><rpPosName Sync="TRUE">Chief</rpPosName><rpCntInfo><cntPhone><voiceNum Sync="TRUE">703-787-1215</voiceNum></cntPhone><cntAddress><delPoint Sync="TRUE">381 Elden Street</delPoint><city Sync="TRUE">Herndon</city><adminArea Sync="TRUE">VA</adminArea><postCode Sync="TRUE">20170</postCode><country Sync="TRUE">USA</country><eMailAdd Sync="TRUE">charlie.broadwater@boem.gov</eMailAdd></cntAddress><cntHours Sync="TRUE">8AM - 5PM EST</cntHours><cntInstr Sync="TRUE">Call</cntInstr></rpCntInfo><role><RoleCd Sync="TRUE" value="007"></RoleCd></role></idPoC></dataIdInfo><mdLang><languageCode value="en"/><countryCode value="USA" Sync="TRUE"/></mdLang><distInfo xmlns=""><distFormat xmlns=""><formatName>zip file</formatName><fileDecmTech>Unzip</fileDecmTech></distFormat><distTranOps xmlns=""><transSize>0.142</transSize></distTranOps><distributor><distorTran><onLineSrc><orDesc Sync="TRUE">002</orDesc><linkage Sync="TRUE">file://\\imsnolna04\Applications\MBB\Workspace\taylorch\metadata test\Sand_Gravel_05112012.shp</linkage><protocol Sync="TRUE">Local Area Network</protocol></onLineSrc><transSize Sync="TRUE">0.059</transSize></distorTran><distorFormat><formatName Sync="TRUE">Shapefile</formatName></distorFormat></distributor></distInfo><mdHrLv><ScopeCd value="005"/></mdHrLv><mdHrLvName>dataset</mdHrLvName><refSysInfo><RefSystem><refSysID><identCode code="4269"/><idCodeSpace>EPSG</idCodeSpace><idVersion>7.4.1</idVersion></refSysID></RefSystem></refSysInfo><spdoinfo><direct>Vector</direct><ptvctinf><esriterm Name="Sand_Gravel_05112012"><efeatyp Sync="TRUE">Simple</efeatyp><efeageom code="4" Sync="TRUE">Polygon</efeageom><esritopo Sync="TRUE">FALSE</esritopo><efeacnt Sync="TRUE">98</efeacnt><spindex Sync="TRUE">TRUE</spindex><linrefer Sync="TRUE">FALSE</linrefer></esriterm><sdtsterm Name="Sand_Gravel_05112012"><sdtstype Sync="TRUE">G-polygon</sdtstype><ptvctcnt Sync="TRUE">98</ptvctcnt></sdtsterm></ptvctinf></spdoinfo><spatRepInfo><VectSpatRep><topLvl><TopoLevCd value="001" Sync="TRUE"/></topLvl><geometObjs Name="Sand_Gravel_05112012"><geoObjTyp><GeoObjTypCd Sync="TRUE" value="001"></GeoObjTypCd></geoObjTyp><geoObjCnt Sync="TRUE">98</geoObjCnt></geometObjs></VectSpatRep></spatRepInfo><eainfo><detailed Name="Sand_Gravel_05112012" xmlns=""><enttyp><enttypl>Sand_Gravel_05112012</enttypl><enttypt Sync="TRUE">Feature Class</enttypt><enttypc Sync="TRUE">98</enttypc></enttyp><attr xmlns=""><attrlabl>FID</attrlabl><attrdef>Internal feature number.</attrdef><attrdefs>ESRI</attrdefs><attrdomv><udom>Sequential unique whole numbers that are automatically generated.</udom></attrdomv><attalias Sync="TRUE">FID</attalias><attrtype Sync="TRUE">OID</attrtype><attwidth Sync="TRUE">4</attwidth><atprecis Sync="TRUE">0</atprecis><attscale Sync="TRUE">0</attscale></attr><attr xmlns=""><attrlabl>OBJECTID</attrlabl><attrdef>Internal feature number.</attrdef><attrdefs>ESRI</attrdefs><attrdomv><udom>Sequential unique whole numbers that are automatically generated.</udom></attrdomv><attalias Sync="TRUE">OBJECTID</attalias><attrtype Sync="TRUE">Integer</attrtype><attwidth Sync="TRUE">9</attwidth><atprecis Sync="TRUE">9</atprecis><attscale Sync="TRUE">0</attscale></attr><attr xmlns=""><attrlabl>Shape</attrlabl><attrdef>Feature geometry.</attrdef><attrdefs>ESRI</attrdefs><attrdomv><udom>Coordinates defining the features.</udom></attrdomv><attalias Sync="TRUE">Shape</attalias><attrtype Sync="TRUE">Number</attrtype><attwidth Sync="TRUE">9</attwidth></attr><attr xmlns=""><attrlabl>AreaName</attrlabl><attrdef>General Name of the resource area depicted such as shoal name</attrdef><attrdefs>BOEM</attrdefs><attrdomv><udom>Name of Resource Area</udom></attrdomv><attalias Sync="TRUE">AreaName</attalias><attrtype Sync="TRUE">String</attrtype><attwidth Sync="TRUE">254</attwidth></attr><attr xmlns=""><attrlabl>State</attrlabl><attrdef>Closest coastal state to the resource depicted</attrdef><attrdefs>BOEM</attrdefs><attrdomv><udom>Closest State Name Acronym</udom></attrdomv><attalias Sync="TRUE">State</attalias><attrtype Sync="TRUE">String</attrtype><attwidth Sync="TRUE">2</attwidth></attr><attr xmlns=""><attrlabl>Info</attrlabl><attrdef>Type of Resource ABA or PBA (Available or Probable Borrow Area)</attrdef><attrdefs>BOEM</attrdefs><attalias Sync="TRUE">Info</attalias><attrtype Sync="TRUE">String</attrtype><attwidth Sync="TRUE">254</attwidth></attr><attr xmlns=""><attrlabl>Link</attrlabl><attrdef>URL Link to supporting document defining the area depicted</attrdef><attrdefs>BOEM</attrdefs><attalias Sync="TRUE">Link</attalias><attrtype Sync="TRUE">String</attrtype><attwidth Sync="TRUE">254</attwidth></attr><attr xmlns=""><attrlabl>ProjectNO</attrlabl><attrdef>BOEM Internal Use</attrdef><attrdefs>BOEM</attrdefs><attalias Sync="TRUE">ProjectNO</attalias><attrtype Sync="TRUE">Number</attrtype><attwidth Sync="TRUE">9</attwidth></attr><attr xmlns=""><attrlabl>Shape_Leng</attrlabl><attalias Sync="TRUE">Shape_Leng</attalias><attrtype Sync="TRUE">Float</attrtype><attwidth Sync="TRUE">19</attwidth><atnumdec Sync="TRUE">11</atnumdec></attr><attr xmlns=""><attrlabl>Shape_Area</attrlabl><attrdef>Area of feature in internal units squared.</attrdef><attrdefs>ESRI</attrdefs><attrdomv><udom>Positive real numbers that are automatically generated.</udom></attrdomv><attalias Sync="TRUE">Shape_Area</attalias><attrtype Sync="TRUE">Float</attrtype><attwidth Sync="TRUE">19</attwidth><atnumdec Sync="TRUE">11</atnumdec></attr></detailed></eainfo><mdDateSt>20120510</mdDateSt><idinfo><descript><abstract>This data set contains both Authorized Borrow Areas (ABAs) and Potential Borrow Areas (PBAs), in ESRI shape file format, for the Atlantic and Gulf of Mexico Regions. These areas are not precise coordinates and may be off from the actual defined areas. There are two terms used Authorized Borrow Areas and Potential Borrow Areas. An Authorized Borrow Area can be defined as a specific area identified for use in a specific project (or that has been used previously in a nourishment project). A Potential Borrow Area can be defined as an area where work is being done to identify a specific borrow area (studies, recon, etc.).</abstract><purpose>These areas will provide users a more accurate delineation of sand that has a high potential for use in shore protection, beach nourishment and/or wetlands restoration projects.
</purpose><supplinf>There are two terms used Authorized Borrow Areas and Potential Borrow Areas.  An Authorized Borrow Area can be defined as a specific area identified for use in a specific project (or that has been used previously in a nourishment project).  A Potential Borrow Area can be defined as an area where work is being done to identify a specific borrow area (studies, recon, etc.).</supplinf><langdata Sync="TRUE">en</langdata></descript><ptcontac><cntinfo><cntperp><cntorg>Office of Strategic Resources, Bureau of Ocean Energy Management</cntorg><cntper>Division Chief, Leasing</cntper></cntperp><cntpos>Division Chief</cntpos><hours>8 AM - 5PM EST</hours><cntinst>Call </cntinst><cntvoice>703-787-1215</cntvoice><cntaddr><addrtype>Address</addrtype><country>USA</country><state>VA</state><city>Herndon</city><postal>20170</postal><address>381 Elden Street</address></cntaddr></cntinfo></ptcontac><accconst>None</accconst><useconst>General Information Only.  Not for legal purposes.  Not for navigational purposes.</useconst><datacred>Christine Taylor and Charlie Broadwater.  Leasing Division, Office of Strategic Resources, Bureau of Ocean Energy Management, Dept. of Interior</datacred><citation><citeinfo><title>Sand_Gravel_05112012</title><ftname Sync="TRUE">Sand_Gravel_05112012</ftname><geoform Sync="TRUE">vector digital data</geoform><origin>Leasing Division, Bureau of Ocean Energy Management</origin><pubdate>Unpublished Material</pubdate><onlink Sync="TRUE">\\imsnolna04\Applications\MBB\Workspace\taylorch\metadata test\Sand_Gravel_05112012.shp</onlink></citeinfo></citation><status><progress>Updated as Needed</progress><update>05112011</update></status><keywords><theme><themekt>Beach Replenishment</themekt><themekey>Sand</themekey><themekey>Gravel</themekey><themekey>Minerals</themekey><themekey>Beach Replenishment</themekey><themekey>Dredge</themekey></theme><theme><themekt>Dredge</themekt></theme><theme><themekt>Gravel</themekt></theme><theme><themekt>Minerals</themekt></theme><theme><themekt>Sand </themekt></theme><place><placekt>Atlantic Ocean</placekt></place><place><placekt>Gulf of Mexico</placekt></place><place><placekt>Mid Atlantic</placekt></place><place><placekt>South Atlantic</placekt></place></keywords><native>Microsoft Windows XP Version 5.1 (Build 2600) Service Pack 3; ESRI ArcGIS 10.0.0.2414</native><spdom><bounding><westbc>-93.7626499992979</westbc><eastbc>-75.0298625508159</eastbc><northbc>38.2608333260973</northbc><southbc>26.3899500000926</southbc></bounding><lboundng><leftbc Sync="TRUE">-93.762650</leftbc><rightbc Sync="TRUE">-75.029863</rightbc><bottombc Sync="TRUE">26.389950</bottombc><topbc Sync="TRUE">38.260833</topbc></lboundng></spdom><natvform Sync="TRUE">Shapefile</natvform><timeperd><current>publication date</current></timeperd><secinfo><secclass>Unclassified</secclass></secinfo></idinfo><dataqual><lineage><procstep><procdesc>Copy Shape files from individual shape files compiled for individual projects.  </procdesc><procdate>05112012</procdate></procstep><procstep><procdesc>Merge data layers</procdesc></procstep></lineage></dataqual><metainfo><metd>20120510</metd><langmeta Sync="TRUE">en</langmeta><metstdn Sync="TRUE">FGDC Content Standards for Digital Geospatial Metadata</metstdn><metstdv Sync="TRUE">FGDC-STD-001-1998</metstdv><mettc Sync="TRUE">local time</mettc><metrd>20120702</metrd><metextns><onlink Sync="TRUE">http://www.esri.com/metadata/esriprof80.html</onlink><metprof Sync="TRUE">ESRI Metadata Profile</metprof></metextns></metainfo><spref><horizsys><geodetic><horizdn>D_North_American_1983</horizdn><ellips>GRS_1980</ellips><semiaxis>6378137</semiaxis><denflat Sync="TRUE">298.257222</denflat></geodetic><cordsysn><geogcsn Sync="TRUE">GCS_North_American_1983</geogcsn></cordsysn><geograph><geogunit Sync="TRUE">Decimal degrees</geogunit><latres>0.001</latres><longres>0.001</longres></geograph></horizsys></spref><mdStanName>FGDC </mdStanName><mdChar><CharSetCd value="005"/></mdChar><Esri xmlns:esri="http://www.esri.com/metadata/"><ArcGISFormat>1.0</ArcGISFormat><ArcGISProfile>FGDC</ArcGISProfile><DataProperties><lineage><Process export="False" Name="" ToolSource=""/></lineage><itemProps><itemSize Sync="TRUE">0.059</itemSize><itemName Sync="TRUE">Sand_Gravel_05112012</itemName><imsContentType Sync="TRUE" export="False">002</imsContentType><nativeExtBox><westBL Sync="TRUE">-93.762650</westBL><eastBL Sync="TRUE">-75.029863</eastBL><southBL Sync="TRUE">26.389950</southBL><northBL Sync="TRUE">38.260833</northBL><exTypeCode Sync="TRUE">1</exTypeCode></nativeExtBox><itemLocation><linkage Sync="TRUE">file://\\imshrnna1\groups\GIS Exchange\taylor_keepout\sand and gravel\editing\Sand_Gravel_05112012.shp</linkage><protocol Sync="TRUE">Local Area Network</protocol></itemLocation></itemProps><coordRef><type Sync="TRUE">Geographic</type><geogcsn Sync="TRUE">GCS_North_American_1983</geogcsn><csUnits Sync="TRUE">Angular Unit: Degree (0.017453)</csUnits><peXml Sync="TRUE">&lt;GeographicCoordinateSystem xsi:type='typens:GeographicCoordinateSystem' xmlns:xsi='http://www.w3.org/2001/XMLSchema-instance' xmlns:xs='http://www.w3.org/2001/XMLSchema' xmlns:typens='http://www.esri.com/schemas/ArcGIS/10.0'&gt;&lt;WKT&gt;GEOGCS[&amp;quot;GCS_North_American_1983&amp;quot;,DATUM[&amp;quot;D_North_American_1983&amp;quot;,SPHEROID[&amp;quot;GRS_1980&amp;quot;,6378137.0,298.257222101]],PRIMEM[&amp;quot;Greenwich&amp;quot;,0.0],UNIT[&amp;quot;Degree&amp;quot;,0.0174532925199433],AUTHORITY[&amp;quot;EPSG&amp;quot;,4269]]&lt;/WKT&gt;&lt;XOrigin&gt;-399.99999999999989&lt;/XOrigin&gt;&lt;YOrigin&gt;-399.99999999999989&lt;/YOrigin&gt;&lt;XYScale&gt;11258999068426.24&lt;/XYScale&gt;&lt;ZOrigin&gt;-100000&lt;/ZOrigin&gt;&lt;ZScale&gt;10000&lt;/ZScale&gt;&lt;MOrigin&gt;-100000&lt;/MOrigin&gt;&lt;MScale&gt;10000&lt;/MScale&gt;&lt;XYTolerance&gt;8.9831528411952117e-009&lt;/XYTolerance&gt;&lt;ZTolerance&gt;0.001&lt;/ZTolerance&gt;&lt;MTolerance&gt;0.001&lt;/MTolerance&gt;&lt;HighPrecision&gt;true&lt;/HighPrecision&gt;&lt;LeftLongitude&gt;-180&lt;/LeftLongitude&gt;&lt;WKID&gt;4269&lt;/WKID&gt;&lt;/GeographicCoordinateSystem&gt;</peXml></coordRef></DataProperties><SyncDate>20120702</SyncDate><SyncTime>14205100</SyncTime><ModDate>20120702</ModDate><ModTime>14205100</ModTime></Esri><mdMaint xmlns=""><maintFreq><MaintFreqCd value="009"/></maintFreq><maintScp><ScopeCd value="005"/></maintScp></mdMaint><dqInfo xmlns=""><dqScope><scpLvl><ScopeCd value="005"></ScopeCd></scpLvl></dqScope></dqInfo><mdStanVer Sync="TRUE">DIS_ESRI1.0</mdStanVer><distinfo><resdesc Sync="TRUE">Downloadable Data</resdesc><stdorder><digform><digtinfo><transize Sync="TRUE">0.059</transize><dssize Sync="TRUE">0.059</dssize></digtinfo></digform><fees>none</fees></stdorder><distrib><cntinfo><cntorgp><cntorg>Leasing Division - Office of Strategic Resources, Bureau of Ocean Energy Management</cntorg></cntorgp><cntaddr><addrtype>mailing and physical address</addrtype><address>381 Elden Street</address><city>Herndon</city><state>VA</state><postal>20170</postal><country>USA</country></cntaddr><cntvoice>703-787-1215</cntvoice></cntinfo></distrib></distinfo></metadata>
